{
    "intro": "Im always learning and mastering new things in computer science.\n There are some of the major languages, technologies, tools I have worked with:",
  "skills": [
    {
      "title": "Languages & Databases",
      "items": [
        {
          "icon": "images/skills/java.png",
          "title": "Java"
        },
        {
          "icon": "images/skills/php.png",
          "title": "PHP"
        },
        {
          "icon": "images/skills/js.png",
          "title": "JavaScript"
        },
        {
          "icon": "images/skills/python.png",
          "title": "Python"
        },
        {
          "icon": "images/skills/mysql.png",
          "title": "MySQL"
        },
        {
          "icon": "images/skills/cLogo.png",
          "title": "C, C#, C++"
        }
      ]
    },

    {
      "title": "Game Engine & Technologies",
      "items": [
      ]
    },

    {
      "title": "Tools & Platforms",
      "items": [
        {
          "icon": "images/skills/git.png",
          "title": "Git"
        }
      ]
    }
  ]
}